Metadata-Version: 2.4
Name: far-search-crewai
Version: 1.0.0
Summary: CrewAI tool for Federal Acquisition Regulations (FAR) search - multi-agent compliance
Home-page: https://github.com/blueskylineassets/far-search-tool
Author: Daniel Chang
Author-email: yschang@blueskylineassets.com
Project-URL: Homepage, https://github.com/blueskylineassets/far-search-tool
Project-URL: Documentation, https://github.com/blueskylineassets/far-search-tool#readme
Project-URL: RapidAPI, https://rapidapi.com/yschang/api/far-rag-federal-acquisition-regulation-search
Keywords: crewai,far,federal-acquisition-regulations,government-contracting,multi-agent,ai-agent,compliance,crew
Classifier: Development Status :: 4 - Beta
Classifier: Intended Audience :: Developers
Classifier: Topic :: Software Development :: Libraries :: Python Modules
Classifier: License :: OSI Approved :: MIT License
Classifier: Programming Language :: Python :: 3
Classifier: Programming Language :: Python :: 3.10
Classifier: Programming Language :: Python :: 3.11
Classifier: Programming Language :: Python :: 3.12
Requires-Python: >=3.10
License-File: LICENSE
Requires-Dist: requests>=2.28.0
Requires-Dist: pydantic>=2.0.0
Provides-Extra: crewai
Requires-Dist: crewai>=0.28.0; extra == "crewai"
Requires-Dist: crewai-tools>=0.2.0; extra == "crewai"
Dynamic: author
Dynamic: author-email
Dynamic: classifier
Dynamic: description
Dynamic: description-content-type
Dynamic: home-page
Dynamic: keywords
Dynamic: license-file
Dynamic: project-url
Dynamic: provides-extra
Dynamic: requires-dist
Dynamic: requires-python
Dynamic: summary
